README.rst
setup.cfg
setup.py
tokenbox.py
tokenbox.egg-info/PKG-INFO
tokenbox.egg-info/SOURCES.txt
tokenbox.egg-info/dependency_links.txt
tokenbox.egg-info/requires.txt
tokenbox.egg-info/top_level.txt