Metadata-Version: 1.2
Name: tokenbox
Version: 1.1.1.dev0
Summary: RESTful API token management utility
Home-page: https://github.com/jjorissen52/tokenbox
Author: John-Paul Jorissen
Author-email: jjorissen52@gmail.com
License: Apache
Keywords: RESTful API Authorization Token Storage
Platform: UNKNOWN
Classifier: Development Status :: 3 - Alpha
Classifier: Intended Audience :: Developers
Classifier: Programming Language :: Python :: 3.6
Classifier: Operating System :: Microsoft :: Windows :: Windows 10
Classifier: Operating System :: POSIX :: Linux
Classifier: Topic :: Office/Business
Classifier: License :: OSI Approved :: Apache Software License
Classifier: Programming Language :: Python :: 3.6
Requires-Python: >=3.6
